Metadata-Version: 1.0
Name: distribut-mlnd
Version: 0.1
Summary: Gaussian and Binomial distributions
Home-page: UNKNOWN
Author: Rasmus Toivanen
Author-email: rasmus.toivanen@hotmail.com
License: UNKNOWN
Platform: UNKNOWN
